odoo/addons/sale_coupon_multiple_code_program/README.rst
odoo/addons/sale_coupon_multiple_code_program/__init__.py
odoo/addons/sale_coupon_multiple_code_program/__manifest__.py
odoo/addons/sale_coupon_multiple_code_program/i18n/sale_coupon_multiple_code_program.pot
odoo/addons/sale_coupon_multiple_code_program/models/__init__.py
odoo/addons/sale_coupon_multiple_code_program/models/coupon_program.py
odoo/addons/sale_coupon_multiple_code_program/models/sale_order.py
odoo/addons/sale_coupon_multiple_code_program/readme/CONTRIBUTORS.rst
odoo/addons/sale_coupon_multiple_code_program/readme/DESCRIPTION.rst
odoo/addons/sale_coupon_multiple_code_program/readme/USAGE.rst
odoo/addons/sale_coupon_multiple_code_program/static/description/icon.png
odoo/addons/sale_coupon_multiple_code_program/static/description/icon.svg
odoo/addons/sale_coupon_multiple_code_program/static/description/index.html
odoo/addons/sale_coupon_multiple_code_program/tests/__init__.py
odoo/addons/sale_coupon_multiple_code_program/tests/test_sale_coupon_multiple_code_program.py
odoo/addons/sale_coupon_multiple_code_program/views/coupon_program_views.xml
odoo/addons/sale_coupon_multiple_code_program/wizards/__init__.py
odoo/addons/sale_coupon_multiple_code_program/wizards/sale_coupon_apply_code.py
odoo_addon_sale_coupon_multiple_code_program-15.0.1.0.0.3.dist-info/METADATA
odoo_addon_sale_coupon_multiple_code_program-15.0.1.0.0.3.dist-info/WHEEL
odoo_addon_sale_coupon_multiple_code_program-15.0.1.0.0.3.dist-info/top_level.txt
odoo_addon_sale_coupon_multiple_code_program-15.0.1.0.0.3.dist-info/RECORD
